{"rates": {"MC": {"rate": 1241.163998, "projected": false, "change_24h": 0.0}, "WU": {"rate": 1314.5, "change_24h": 0.77}, "CCL": {"buy": 1323.8, "mid": 1324.1, "sell": 1324.4, "change_24h": 0.58}, "MEP": {"buy": 1326, "mid": 1327.15, "sell": 1328.3, "change_24h": 0.91}, "BLUE": {"buy": 1320, "mid": 1330.0, "sell": 1340, "change_24h": 0.0}, "VISA": {"rate": 1241.163998, "change_24h": 1.21}, "CRYPTO": {"buy": 1333, "mid": 1334.73, "sell": 1336.45, "change_24h": 0.43}, "TARJETA": {"rate": 1735.5, "change_24h": 1.14}, "OFFICIAL": {"buy": 1295, "mid": 1315.0, "sell": 1335, "change_24h": 1.14}}, "labels": {"MC": "Mastercard", "WU": "Western Union", "CCL": "D\u00f3lar CCL", "MEP": "D\u00f3lar MEP", "BLUE": "D\u00f3lar Blue", "VISA": "Visa", "CRYPTO": "D\u00f3lar Cripto", "TARJETA": "D\u00f3lar Tarjeta", "OFFICIAL": "D\u00f3lar Official"}, "timestamp": "2025-08-22T13:45:21.167533-03:00", "last_updated": "2025-08-22T16:45:21.501900"}