{"rates": {"MC": {"rate": 1075.186039, "projected": false, "change_24h": 0.0}, "WU": {"rate": 1157, "change_24h": -0.17}, "CCL": {"buy": 1163.72, "mid": 1165.91, "sell": 1168.1, "change_24h": -0.52}, "MEP": {"buy": 1147.88, "mid": 1148.2, "sell": 1148.51, "change_24h": -0.71}, "BLUE": {"buy": 1145, "mid": 1155.0, "sell": 1165, "change_24h": 0.0}, "VISA": {"rate": 1075.186039, "change_24h": -0.31}, "CRYPTO": {"buy": null, "mid": null, "sell": null, "change_24h": 0}, "TARJETA": {"rate": 1501.5, "change_24h": -0.43}, "OFFICIAL": {"buy": 1102.79, "mid": 1127.74, "sell": 1152.69, "change_24h": -0.63}}, "labels": {"MC": "Mastercard", "WU": "Western Union", "CCL": "D\u00f3lar CCL", "MEP": "D\u00f3lar MEP", "BLUE": "D\u00f3lar Blue", "VISA": "Visa", "CRYPTO": "D\u00f3lar Cripto", "TARJETA": "D\u00f3lar Tarjeta", "OFFICIAL": "D\u00f3lar Official"}, "timestamp": "2025-05-20T04:00:45.649531-03:00", "last_updated": "2025-05-20T07:00:45.805424"}