{"rates": {"MC": {"rate": 1106.668941, "projected": false, "change_24h": 0.0}, "WU": {"rate": 1187.05, "change_24h": 0.94}, "CCL": {"buy": 1208.3, "mid": 1208.6, "sell": 1208.9, "change_24h": 1.47}, "MEP": {"buy": 1192.2, "mid": 1195.7, "sell": 1199.2, "change_24h": 1.52}, "BLUE": {"buy": 1160, "mid": 1170.0, "sell": 1180, "change_24h": 0.85}, "VISA": {"rate": 1106.668941, "change_24h": 1.78}, "CRYPTO": {"buy": 1211, "mid": 1212.25, "sell": 1213.49, "change_24h": 1.86}, "TARJETA": {"rate": 1553.5, "change_24h": 0.0}, "OFFICIAL": {"buy": 1145, "mid": 1170.0, "sell": 1195, "change_24h": 0.0}}, "labels": {"MC": "Mastercard", "WU": "Western Union", "CCL": "D\u00f3lar CCL", "MEP": "D\u00f3lar MEP", "BLUE": "D\u00f3lar Blue", "VISA": "Visa", "CRYPTO": "D\u00f3lar Cripto", "TARJETA": "D\u00f3lar Tarjeta", "OFFICIAL": "D\u00f3lar Official"}, "timestamp": "2025-05-30T14:00:19.18944-03:00", "last_updated": "2025-05-30T17:00:19.506199"}