{"rates": {"MC": {"rate": 1071.994048, "projected": false, "change_24h": 0.0}, "WU": {"rate": 1143.25, "change_24h": -0.26}, "CCL": {"buy": 1147.48, "mid": 1149.21, "sell": 1150.94, "change_24h": 0.23}, "MEP": {"buy": 1135.4, "mid": 1135.56, "sell": 1135.72, "change_24h": 0.28}, "BLUE": {"buy": 1155, "mid": 1165.0, "sell": 1175, "change_24h": 0.0}, "VISA": {"rate": 1071.994048, "change_24h": -0.86}, "CRYPTO": {"buy": null, "mid": null, "sell": null, "change_24h": 0.0}, "TARJETA": {"rate": 1469, "change_24h": -1.74}, "OFFICIAL": {"buy": 1077.84, "mid": 1102.79, "sell": 1127.74, "change_24h": -1.74}}, "labels": {"MC": "Mastercard", "WU": "Western Union", "CCL": "D\u00f3lar CCL", "MEP": "D\u00f3lar MEP", "BLUE": "D\u00f3lar Blue", "VISA": "Visa", "CRYPTO": "D\u00f3lar Cripto", "TARJETA": "D\u00f3lar Tarjeta", "OFFICIAL": "D\u00f3lar Official"}, "timestamp": "2025-05-09T14:00:45.555002-03:00", "last_updated": "2025-05-09T17:00:45.732798"}