{"rates": {"MC": {"rate": 1073.979003, "projected": false, "change_24h": 0.0}, "WU": {"rate": 1159.75, "change_24h": 0.76}, "CCL": {"buy": 1167.4, "mid": 1167.6, "sell": 1167.8, "change_24h": 0.55}, "MEP": {"buy": 1153.4, "mid": 1153.75, "sell": 1154.1, "change_24h": 0.8}, "BLUE": {"buy": 1145, "mid": 1155.0, "sell": 1165, "change_24h": 0.43}, "VISA": {"rate": 1073.979003, "change_24h": 0.54}, "CRYPTO": {"buy": 1169.4, "mid": 1171.8, "sell": 1174.19, "change_24h": 0.36}, "TARJETA": {"rate": 1495, "change_24h": 0.0}, "OFFICIAL": {"buy": 1100, "mid": 1125.0, "sell": 1150, "change_24h": 0.0}}, "labels": {"MC": "Mastercard", "WU": "Western Union", "CCL": "D\u00f3lar CCL", "MEP": "D\u00f3lar MEP", "BLUE": "D\u00f3lar Blue", "VISA": "Visa", "CRYPTO": "D\u00f3lar Cripto", "TARJETA": "D\u00f3lar Tarjeta", "OFFICIAL": "D\u00f3lar Official"}, "timestamp": "2025-05-16T12:00:11.932914-03:00", "last_updated": "2025-05-16T15:00:12.104397"}