{"rates": {"MC": {"rate": 1189.067004, "projected": false, "change_24h": 0.0}, "WU": {"rate": 1270.55, "change_24h": -0.31}, "CCL": {"buy": 1268.4, "mid": 1268.95, "sell": 1269.5, "change_24h": 0.17}, "MEP": {"buy": 1265.7, "mid": 1266.9, "sell": 1268.1, "change_24h": 0.21}, "BLUE": {"buy": 1270, "mid": 1280.0, "sell": 1290, "change_24h": -1.53}, "VISA": {"rate": 1189.067004, "change_24h": -0.04}, "CRYPTO": {"buy": 1281, "mid": 1282.24, "sell": 1283.48, "change_24h": 0.04}, "TARJETA": {"rate": 1657.5, "change_24h": -0.39}, "OFFICIAL": {"buy": 1225, "mid": 1250.0, "sell": 1275, "change_24h": -0.39}}, "labels": {"MC": "Mastercard", "WU": "Western Union", "CCL": "D\u00f3lar CCL", "MEP": "D\u00f3lar MEP", "BLUE": "D\u00f3lar Blue", "VISA": "Visa", "CRYPTO": "D\u00f3lar Cripto", "TARJETA": "D\u00f3lar Tarjeta", "OFFICIAL": "D\u00f3lar Official"}, "timestamp": "2025-07-17T12:00:12.74627-03:00", "last_updated": "2025-07-17T15:00:12.894023"}