{"rates": {"MC": {"rate": 1213.001042, "projected": false, "change_24h": 0.0}, "WU": {"rate": 1292.5, "change_24h": 2.31}, "CCL": {"buy": 1300.9, "mid": 1301.2, "sell": 1301.5, "change_24h": 0.67}, "MEP": {"buy": 1299.5, "mid": 1300.2, "sell": 1300.9, "change_24h": 0.63}, "BLUE": {"buy": 1295, "mid": 1305.0, "sell": 1315, "change_24h": 0.0}, "VISA": {"rate": 1213.001042, "change_24h": 0.93}, "CRYPTO": {"buy": 1308.2, "mid": 1310.84, "sell": 1313.48, "change_24h": 0.88}, "TARJETA": {"rate": 1703, "change_24h": 1.16}, "OFFICIAL": {"buy": 1260, "mid": 1285.0, "sell": 1310, "change_24h": 1.16}}, "labels": {"MC": "Mastercard", "WU": "Western Union", "CCL": "D\u00f3lar CCL", "MEP": "D\u00f3lar MEP", "BLUE": "D\u00f3lar Blue", "VISA": "Visa", "CRYPTO": "D\u00f3lar Cripto", "TARJETA": "D\u00f3lar Tarjeta", "OFFICIAL": "D\u00f3lar Official"}, "timestamp": "2025-07-29T12:45:13.029367-03:00", "last_updated": "2025-07-29T15:45:13.204609"}