{"rates": {"MC": {"rate": 1234.241055, "projected": false, "change_24h": 0.0}, "WU": {"rate": 1315, "change_24h": 0.91}, "CCL": {"buy": 1309, "mid": 1312.3, "sell": 1315.6, "change_24h": 0.19}, "MEP": {"buy": 1308.5, "mid": 1309.3, "sell": 1310.1, "change_24h": -0.33}, "BLUE": {"buy": 1295, "mid": 1305.0, "sell": 1315, "change_24h": 0.0}, "VISA": {"rate": 1234.241055, "change_24h": -0.77}, "CRYPTO": {"buy": 1327.4, "mid": 1328.2, "sell": 1329, "change_24h": -0.08}, "TARJETA": {"rate": 1422.53, "change_24h": 0.02}, "OFFICIAL": {"buy": 1054.25, "mid": 1074.25, "sell": 1094.25, "change_24h": 0.02}}, "labels": {"MC": "Mastercard", "WU": "Western Union", "CCL": "D\u00f3lar CCL", "MEP": "D\u00f3lar MEP", "BLUE": "D\u00f3lar Blue", "VISA": "Visa", "CRYPTO": "D\u00f3lar Cripto", "TARJETA": "D\u00f3lar Tarjeta", "OFFICIAL": "D\u00f3lar Official"}, "timestamp": "2025-04-02T12:45:12.250427-03:00", "last_updated": "2025-04-02T15:45:12.616024"}