{"rates": {"MC": {"rate": 1151.849997, "projected": false, "change_24h": 0.0}, "WU": {"rate": 1225.35, "change_24h": -0.06}, "CCL": {"buy": 1230.6, "mid": 1231.0, "sell": 1231.4, "change_24h": 0.29}, "MEP": {"buy": 1229.9, "mid": 1231.05, "sell": 1232.2, "change_24h": 0.37}, "BLUE": {"buy": 1210, "mid": 1220.0, "sell": 1230, "change_24h": 0.0}, "VISA": {"rate": 1151.849997, "change_24h": -0.02}, "CRYPTO": {"buy": 1241, "mid": 1242.15, "sell": 1243.3, "change_24h": 0.02}, "TARJETA": {"rate": 1412.45, "change_24h": 0.02}, "OFFICIAL": {"buy": 1046.5, "mid": 1066.5, "sell": 1086.5, "change_24h": 0.02}}, "labels": {"MC": "Mastercard", "WU": "Western Union", "CCL": "D\u00f3lar CCL", "MEP": "D\u00f3lar MEP", "BLUE": "D\u00f3lar Blue", "VISA": "Visa", "CRYPTO": "D\u00f3lar Cripto", "TARJETA": "D\u00f3lar Tarjeta", "OFFICIAL": "D\u00f3lar Official"}, "timestamp": "2025-03-13T11:30:21.256524-03:00", "last_updated": "2025-03-13T14:30:21.600050"}