{"rates": {"MC": {"rate": 1293.197985, "projected": false, "change_24h": 0.0}, "WU": {"rate": 1329.65, "change_24h": 0.0}, "CCL": {"buy": 1365.3, "mid": 1365.6, "sell": 1365.9, "change_24h": 0.89}, "MEP": {"buy": 1365.7, "mid": 1366.5, "sell": 1367.3, "change_24h": -0.34}, "BLUE": {"buy": 1350, "mid": 1360.0, "sell": 1370, "change_24h": 1.86}, "VISA": {"rate": 1293.197985, "change_24h": 2.61}, "CRYPTO": {"buy": 1366.38, "mid": 1368.69, "sell": 1371, "change_24h": -0.06}, "TARJETA": {"rate": 1800.5, "change_24h": 1.84}, "OFFICIAL": {"buy": 1345, "mid": 1365.0, "sell": 1385, "change_24h": 1.84}}, "labels": {"MC": "Mastercard", "WU": "Western Union", "CCL": "D\u00f3lar CCL", "MEP": "D\u00f3lar MEP", "BLUE": "D\u00f3lar Blue", "VISA": "Visa", "CRYPTO": "D\u00f3lar Cripto", "TARJETA": "D\u00f3lar Tarjeta", "OFFICIAL": "D\u00f3lar Official"}, "timestamp": "2025-09-02T12:30:13.488305-03:00", "last_updated": "2025-09-02T15:30:13.815764"}